DetectBinod/__init__.py
DetectBinod-0.0.2.dist-info/LICENSE.txt
DetectBinod-0.0.2.dist-info/METADATA
DetectBinod-0.0.2.dist-info/WHEEL
DetectBinod-0.0.2.dist-info/top_level.txt
DetectBinod-0.0.2.dist-info/RECORD
