Metadata-Version: 2.1
Name: DetectBinod
Version: 0.0.2
Summary: Detect Binod In Files
Home-page: UNKNOWN
Author: Akshay Pawar
Author-email: akshupatil665@gmail.com
License: MIT
Platform: UNKNOWN
Classifier: Programming Language :: Python :: 3
Classifier: Operating System :: OS Independent
Requires-Dist: PyPDF2
Requires-Dist: xlrd
Requires-Dist: python-docx
Requires-Dist: python-pptx
